yucebio_config.py
Yucebio_Config-0.1.0.dist-info/METADATA
Yucebio_Config-0.1.0.dist-info/WHEEL
Yucebio_Config-0.1.0.dist-info/top_level.txt
Yucebio_Config-0.1.0.dist-info/RECORD
