Metadata-Version: 2.1
Name: Yucebio-Config
Version: 0.1.0
Summary: 简单的统一配置管理工具
Home-page: UNKNOWN
Author: huangqingjun
Author-email: huangqingjun@yucebio.com
License: MIT
Platform: UNKNOWN
Classifier: License :: OSI Approved :: MIT License
Classifier: Programming Language :: Python
Classifier: Programming Language :: Python :: 3
Classifier: Programming Language :: Python :: 3.8
Classifier: Programming Language :: Python :: Implementation :: CPython
Classifier: Programming Language :: Python :: Implementation :: PyPy
Requires-Python: >=3.8
Requires-Dist: json5
Requires-Dist: icecream
